litmusTest_backend/__init__.py
litmusTest_backend/admin.py
litmusTest_backend/apps.py
litmusTest_backend/models.py
litmusTest_backend/tests.py
litmusTest_backend/views.py
litmusTest_backend/migrations/__init__.py
litmusTest_backend_app-1.0.0.dist-info/LICENSE
litmusTest_backend_app-1.0.0.dist-info/METADATA
litmusTest_backend_app-1.0.0.dist-info/WHEEL
litmusTest_backend_app-1.0.0.dist-info/top_level.txt
litmusTest_backend_app-1.0.0.dist-info/RECORD
